LICENSE
README.md
pyproject.toml
setup.cfg
setup.py
microesb.egg-info/PKG-INFO
microesb.egg-info/SOURCES.txt
microesb.egg-info/dependency_links.txt
microesb.egg-info/top_level.txt
microesb.egg-info/zip-safe
src/esbconfig.py
src/microesb.py
src/router.py
src/testclasses.py
src/transformer.py