Metadata-Version: 2.1
Name: microesb
Version: 1.1.1
Summary: A Small OOP Based Enterprise Service Bus Implementation.
Author: Claus Prüfer
Author-email: Claus Prüfer <pruefer@webcodex.de>
Project-URL: Homepage, https://github.com/clauspruefer/python-micro-esb
Project-URL: Issues, https://github.com/clauspruefer/python-micro-esb
Project-URL: Documentation, https://pythondocs.webcodex.de/micro-esb
Project-URL: Changelog, https://github.com/clauspruefer/python-micro-esb/CHANGELOG.md
Classifier: Programming Language :: Python :: 3
Classifier: License :: OSI Approved :: GNU Affero General Public License v3 or later (AGPLv3+)
Classifier: Operating System :: OS Independent
Requires-Python: >=3.8
License-File: LICENSE
